Workbook

Sheet README
A1: Paramount Resources — Module 5: Comparable Company & Transaction Analysis
A2: Where Paramount trades against its peers, and what acquirers have actually paid for Montney and Duvernay assets.
A4: WHY THIS MODULE EXISTS
A5: The problem with NAV alone | B5: Module 4 produced a NAV of C$31.65 per share, but that number is only as good as its assumptions. Comparables test it against what the market and actual acquirers are paying, which is evidence rather than assumption.
A6: Two kinds of comparable | B6: Trading comps show what public investors pay for a minority stake. Transaction comps show what a strategic buyer pays for control, which normally carries a premium. Both matter and they answer different questions.
A7: The metrics that matter here | B7: Canadian producers are compared on EV to adjusted funds flow, enterprise value per flowing barrel, and enterprise value per barrel of 2P reserves. Price-to-earnings is close to useless in this sector because depletion accounting swamps it.
A9: READ THIS BEFORE USING THE NUMBERS
A10: DATA FRESHNESS | B10: Comps go stale within days. Share prices, share counts and net debt for the peer group are marked in the Data status column. Anything flagged VERIFY is my estimate and must be refreshed from a terminal, SEDAR+ filing or the company's latest release before you quote a single multiple. Production, cash flow and reserve figures are sourced from Q2 2026 releases and are reliable. This is normal — a live comps sheet is refreshed constantly, and knowing which cells are soft is part of the discipline.
A12: THE HEADLINE FINDING
A13: • The Canadian gas peer group is disappearing. ARC Resources agreed to be acquired by Shell in April 2026 for roughly C$22 billion, and Ovintiv closed its acquisition of NuVista in February 2026 for roughly C$3.8 billion. Two of the most obvious Paramount comparables were removed from the market inside four months.
A14: • That consolidation is itself an argument. Scarcity value accrues to the remaining independent Montney and Duvernay operators with owned infrastructure and long inventory — a description that fits Paramount closely.
A15: • Shell explicitly noted that around 40% of ARC's production was liquids but that those liquids generated about 70% of revenue. That is external, third-party confirmation of the six-to-one energy versus value distinction running through this entire project.
A17: Hypothetical case study. Not investment advice.

Sheet Trading_Comps
A1: Trading Comparables — Canadian Gas-Weighted Producers
A2: Blue cells are inputs. All multiples are formulas. Check the Data status column before quoting anything.
A4: Company | B4: Ticker | C4: Price (C$) | D4: Shares (mm) | E4: Mkt cap (C$mm) | F4: Net debt (C$mm) | G4: EV (C$mm) | H4: Q2'26 (Boe/d) | I4: 2026E (Boe/d) | J4: Liq % | K4: AFF ann. (C$mm) | L4: 2P (MBoe) | M4: EV/AFF | N4: EV/flow Q2 | O4: EV/flow 26E | P4: EV/2P | Q4: Data status
A5: Paramount Resources | B5: POU | C5: 32.65 | D5: 145.8 | E5: =IF(N(C5)*N(D5)=0,"n/a",C5*D5) -> 4760.37 | F5: -537.1 | G5: =IF(N(E5)=0,"n/a",E5+N(F5)) -> 4223.27 | H5: 47279 | I5: 52133 | J5: 0.49 | K5: 702.4 | L5: 521518 | M5: =IFERROR(G5/K5,"n/a") -> 6.0126281 | N5: =IFERROR(G5*1000000/H5,"n/a") -> 89326.551 | O5: =IFERROR(G5*1000000/I5,"n/a") -> 81009.533 | P5: =IFERROR(G5*1000/L5,"n/a") -> 8.098033 | Q5: Verified — my model
A6: Tourmaline Oil | B6: TOU | C6: 62 | D6: 389 | E6: =IF(N(C6)*N(D6)=0,"n/a",C6*D6) -> 24118 | F6: 1500 | G6: =IF(N(E6)=0,"n/a",E6+N(F6)) -> 25618 | H6: 594198 | I6: 630000 | J6: 0.13 | K6: 3144.4 | L6: n/a | M6: =IFERROR(G6/K6,"n/a") -> 8.1471823 | N6: =IFERROR(G6*1000000/H6,"n/a") -> 43113.575 | O6: =IFERROR(G6*1000000/I6,"n/a") -> 40663.492 | P6: =IFERROR(G6*1000/L6,"n/a") -> n/a | Q6: VERIFY price & shares
A7: Peyto Exploration | B7: PEY | C7: 24 | D7: 198 | E7: =IF(N(C7)*N(D7)=0,"n/a",C7*D7) -> 4752 | F7: 1250 | G7: =IF(N(E7)=0,"n/a",E7+N(F7)) -> 6002 | H7: 145320 | I7: 148000 | J7: 0.11 | K7: 910.8 | L7: n/a | M7: =IFERROR(G7/K7,"n/a") -> 6.5898112 | N7: =IFERROR(G7*1000000/H7,"n/a") -> 41301.954 | O7: =IFERROR(G7*1000000/I7,"n/a") -> 40554.054 | P7: =IFERROR(G7*1000/L7,"n/a") -> n/a | Q7: VERIFY price, shares, debt
A8: Birchcliff Energy | B8: BIR | C8: 5.93 | D8: 276 | E8: =IF(N(C8)*N(D8)=0,"n/a",C8*D8) -> 1636.68 | F8: 250 | G8: =IF(N(E8)=0,"n/a",E8+N(F8)) -> 1886.68 | H8: 77562 | I8: 83500 | J8: 0.16 | K8: 374.8 | L8: n/a | M8: =IFERROR(G8/K8,"n/a") -> 5.0338314 | N8: =IFERROR(G8*1000000/H8,"n/a") -> 24324.798 | O8: =IFERROR(G8*1000000/I8,"n/a") -> 22594.97 | P8: =IFERROR(G8*1000/L8,"n/a") -> n/a | Q8: Price from Q2 buyback; VERIFY debt
A9: Kelt Exploration | B9: KEL | C9: 6.5 | D9: 190 | E9: =IF(N(C9)*N(D9)=0,"n/a",C9*D9) -> 1235 | F9: 215.1 | G9: =IF(N(E9)=0,"n/a",E9+N(F9)) -> 1450.1 | H9: 48098 | I9: 51000 | J9: 0.35 | K9: 400 | L9: n/a | M9: =IFERROR(G9/K9,"n/a") -> 3.62525 | N9: =IFERROR(G9*1000000/H9,"n/a") -> 30148.863 | O9: =IFERROR(G9*1000000/I9,"n/a") -> 28433.333 | P9: =IFERROR(G9*1000/L9,"n/a") -> n/a | Q9: VERIFY price & shares
A10: Advantage Energy | B10: AAV | C10: n/a | D10: n/a | E10: =IF(N(C10)*N(D10)=0,"n/a",C10*D10) -> n/a | F10: n/a | G10: =IF(N(E10)=0,"n/a",E10+N(F10)) -> n/a | H10: n/a | I10: n/a | J10: n/a | K10: n/a | L10: n/a | M10: =IFERROR(G10/K10,"n/a") -> n/a | N10: =IFERROR(G10*1000000/H10,"n/a") -> n/a | O10: =IFERROR(G10*1000000/I10,"n/a") -> n/a | P10: =IFERROR(G10*1000/L10,"n/a") -> n/a | Q10: NOT POPULATED — add from filings
A11: Peer median (excl. POU) | M11: =IFERROR(MEDIAN(M6:M10),"n/a") -> 5.8118213 | N11: =IFERROR(MEDIAN(N6:N10),"n/a") -> 35725.409 | O11: =IFERROR(MEDIAN(O6:O10),"n/a") -> 34493.694 | P11: =IFERROR(MEDIAN(P6:P10),"n/a") -> n/a
A12: Peer mean (excl. POU) | M12: =IFERROR(AVERAGE(M6:M10),"n/a") -> 5.8490187 | N12: =IFERROR(AVERAGE(N6:N10),"n/a") -> 34722.298 | O12: =IFERROR(AVERAGE(O6:O10),"n/a") -> 33061.462 | P12: =IFERROR(AVERAGE(P6:P10),"n/a") -> n/a
A14: MEDIAN and AVERAGE ignore text entries, so unpopulated peers drop out automatically rather than counting as zero.
A15: 2P reserves are only populated for Paramount. Add peer reserve figures from each company's Annual Information Form to make the EV/2P column meaningful.

Sheet Transaction_Comps
A1: Transaction Comparables — What Acquirers Actually Paid
A2: Control transactions in the Canadian Montney and Duvernay. These carry a control premium that trading comps do not.
A4: Acquirer | B4: Target | C4: Announced | D4: Total value (C$mm) | E4: Production (Boe/d) | F4: 2P (MBoe) | G4: Premium | H4: EV/flowing | I4: EV/2P | J4: Note
A5: Shell plc | B5: ARC Resources | C5: Apr 2026 | D5: 22000 | E5: 370000 | F5: 2000000 | G5: 0.27 | H5: =IFERROR(D5*1000000/E5,"n/a") -> 59459.459 | I5: =IFERROR(D5*1000/F5,"n/a") -> 11 | J5: C$32.80 per share, 75% Shell stock and 25% cash. 1.5mm net Montney acres. Shell disclosed that ~40% liquids generated ~70% of revenue.
A6: Ovintiv | B6: NuVista Energy | C6: Feb 2026 | D6: 3800 | E6: n/a | F6: n/a | G6: n/a | H6: =IFERROR(D6*1000000/E6,"n/a") -> n/a | I6: =IFERROR(D6*1000/F6,"n/a") -> n/a | J6: Closed 3-Feb-2026. Added ~930 net well locations and ~140,000 net acres in the Alberta Montney. VERIFY production to compute multiples.
A8: PARAMOUNT AGAINST THE SHELL / ARC BENCHMARK
A9: Metric | B9: Paramount | C9: Shell / ARC | D9: Paramount vs deal
A10: EV per flowing Boe/d — Q2 2026 actual | B10: =Trading_Comps!N5 -> 89326.551 | C10: =H5 -> 59459.459 | D10: =IFERROR(B10/C10-1,"n/a") -> 0.50231017 | F10: Paramount looks expensive on today's production.
A11: EV per flowing Boe/d — 2026E average | B11: =Trading_Comps!O5 -> 81009.533 | C11: =H5 -> 59459.459 | D11: =IFERROR(B11/C11-1,"n/a") -> 0.36243306 | F11: The gap narrows as guided volumes arrive.
A12: EV per 2P Boe | B12: =Trading_Comps!P5 -> 8.098033 | C12: =I5 -> 11 | D12: =IFERROR(B12/C12-1,"n/a") -> -0.26381518 | F12: And inverts entirely on reserves — Paramount looks cheap.
A14: THE TENSION: Paramount trades at a large premium to the Shell/ARC deal on current production, yet at a discount on 2P reserves. Both are true, and the reconciliation is the investment thesis. Production is about to double while the reserve book already contains Sinclair and the Willesden Green inventory. Buying Paramount means paying up for barrels that exist on paper but are not yet flowing. Whether that is cheap depends entirely on execution.

Sheet Valuation_Bridge
A1: Implied Value per Share — Multiple Methods
A2: Applies peer and transaction multiples to Paramount's own metrics, then compares against Module 4's NAV.
A4: PARAMOUNT INPUTS
A5: Shares outstanding (mm) | B5: =Trading_Comps!D5 -> 145.8
A6: Net cash and investments (C$mm) | B6: =-Trading_Comps!F5 -> 537.1 | F6: Added back to bridge from enterprise value to equity.
A7: Q2 2026 production (Boe/d) | B7: =Trading_Comps!H5 -> 47279
A8: 2026E production (Boe/d) | B8: =Trading_Comps!I5 -> 52133
A9: 2027E production (Boe/d) | B9: 63400 | F9: MODULE 2 output — the year Sinclair starts contributing.
A10: Annualised Q2 2026 AFF (C$mm) | B10: =Trading_Comps!K5 -> 702.4
A11: 2027E AFF (C$mm) | B11: 950 | F11: MODULE 2 Base case.
A12: 2P reserves (MBoe) | B12: =Trading_Comps!L5 -> 521518
A13: Current share price (C$) | B13: =Trading_Comps!C5 -> 32.65
A15: IMPLIED SHARE PRICE BY METHOD
A16: Method | B16: Multiple | C16: Implied EV (C$mm) | D16: Implied C$/share
A17: Shell/ARC EV per flowing Boe/d, on 2027E volumes | B17: =Transaction_Comps!H5 -> 59459.459 | C17: =B17*$B$9/1000000 -> 3769.7297 | D17: =(C17+$B$6)/$B$5 -> 29.539299 | F17: The most defensible single comparison: a control transaction in the same basin, in the same year.
A18: Shell/ARC EV per 2P Boe | B18: =Transaction_Comps!I5 -> 11 | C18: =B18*$B$12/1000 -> 5736.698 | D18: =(C18+$B$6)/$B$5 -> 43.030165 | F18: Rewards Paramount's large undeveloped reserve book.
A19: Peer median EV/AFF, on 2027E adjusted funds flow | B19: =Trading_Comps!M11 -> 5.8118213 | C19: =B19*$B$11 -> 5521.2302 | D19: =(C19+$B$6)/$B$5 -> 41.552333 | F19: Cash-flow based. Check the peer inputs before trusting this.
A20: Peer median EV per flowing Boe/d, on 2027E volumes | B20: =Trading_Comps!N11 -> 35725.409 | C20: =B20*$B$9/1000000 -> 2264.9909 | D20: =(C20+$B$6)/$B$5 -> 19.21873 | F20: Minority-stake valuation, so no control premium.
A21: Low | D21: =IFERROR(MIN(D17:D20),"n/a") -> 19.21873
A22: Median | D22: =IFERROR(MEDIAN(D17:D20),"n/a") -> 35.545816
A23: High | D23: =IFERROR(MAX(D17:D20),"n/a") -> 43.030165
A25: TRIANGULATION — the three independent routes to a value
A26: Method | B26: C$/share | C26: vs market
A27: Module 4 — sum-of-the-parts NAV | B27: 31.65 | C27: =IFERROR(B27/$B$13-1,"n/a") -> -0.030627871 | F27: Bottom-up asset valuation. Hardcoded here; refresh if the NAV assumptions change.
A28: Module 5 — comparables median | B28: =D22 -> 35.545816 | C28: =IFERROR(B28/$B$13-1,"n/a") -> 0.088692679 | F28: What the market and acquirers are paying for similar barrels.
A29: Market price today | B29: =$B$13 -> 32.65 | C29: =IFERROR(B29/$B$13-1,"n/a") -> 0 | F29: What you can actually buy it for.
A32: HOW TO USE THIS: if NAV and comparables both land near the market price, the stock is fairly valued and there is no thesis. If they diverge, the divergence is the thesis — and you must be able to explain why the market disagrees with you.
A33: The most common error at this stage is quietly discarding whichever method gives the inconvenient answer. Show all of them, weight them explicitly, and say which you trust most and why.
