Workbook

Sheet README
A1: Paramount Resources Ltd. (TSX: POU) — PE Take-Private Case Study
A2: Module 1: Data Book. Every figure below is sourced from public disclosure. All downstream models reference this file.
A4: PURPOSE
A5: This workbook | B5: Single source of truth. Historical financials, operating data, reserves, guidance, capital structure and the price deck.
A6: What it is not | B6: It contains no forecast of the business. The operating model, NAV, LBO and Monte Carlo modules are built separately and link here.
A7: Rule | B7: No downstream module should hardcode a POU figure. If a number is needed, add it here first with its source, then reference it.
A9: COLOUR LEGEND (financial modelling convention)
A10: Blue text | B10: Hardcoded input taken from a source document, or a scenario lever you may change.
A11: Black text | B11: Formula calculated within the sheet.
A12: Green text | B12: Link to another sheet in this workbook.
A13: Yellow fill | B13: Key assumption. These are the cells that drive the case — review before every run.
A15: TAB GUIDE
A16: Snapshot | B16: Market data, capitalisation, enterprise value, ownership. The two blue cells at top are the only market inputs to refresh.
A17: Financials_Hist | B17: Quarterly and annual income, cash flow and balance sheet items, FY2024 through Q2 2026.
A18: Production_Ops | B18: Sales volumes by asset and product type; realised prices; netback build; unit operating costs.
A19: Reserves | B19: McDaniel report effective 31-Dec-2025: PDP / TP / P+P volumes, before-tax NPV, reserve life, F&D and recycle ratios.
A20: Guidance | B20: Company guidance for 2026 and 2027, including the capital programme by asset and the 2027 exit-rate target.
A21: Assets | B21: Asset-by-asset descriptors: land, processing capacity, egress, well results, plateau targets. Inputs to the type-curve work.
A22: Hedges_Credit | B22: Hedge book and credit facilities as disclosed at Q2 2026.
A23: PriceDeck | B23: Bear / Base / Bull commodity assumptions. THE central scenario lever — the Monte Carlo module samples around these.
A24: Derived_Metrics | B24: Live trading multiples calculated off Snapshot, Reserves and Production_Ops.
A26: PRIMARY SOURCES
A27: Q2 2026 results (6-Aug-2026) | B27: paramount.mediaroom.com — Q2 2026 press release. Volumes, netbacks, capex by asset, hedges, guidance.
A28: FY2025 results (3-Mar-2026) | B28: paramount.mediaroom.com — Q4/annual 2025 press release. Reserves tables, FY financials, 2026-27 capital outlook.
A29: 2025 Annual Information Form | B29: paramountres.com — full McDaniel reserves disclosure, land, risk factors.
A30: SEDAR+ | B30: sedarplus.ca — financial statements and MD&A.
A31: Market data | B31: TSX close and consensus targets. Refresh the two blue cells on Snapshot before each run.
A34: Hypothetical case study for analytical purposes. Not investment advice, and not a recommendation to buy or sell any security.

Sheet Snapshot
A1: Company Snapshot & Capitalisation
A2: Balance sheet items as at 30-Jun-2026 (Q2 2026 press release). Market data as at the date shown — refresh the blue cells.
A4: MARKET INPUTS — refresh these two cells
A5: Market data as at | B5: 21-Aug-2026 | D5: Update whenever you re-run the case.
A6: Share price (C$/share) | B6: 32.65 | D6: TSX close. Implied by consensus target of ~C$37.10 quoted at +13.7%.
A7: Consensus analyst target (C$/share) | B7: 37.1 | D7: 10 analysts. Recent targets: RBC C$37, Scotiabank C$36, CIBC C$34.
A9: SHARE COUNT & MARKET CAPITALISATION
A10: Common shares outstanding (mm) | B10: 145.8 | D10: Q2 2026, net of 0.1mm shares held in trust under the RSU plan.
A11: Market capitalisation (C$mm) | B11: =B6*B10 -> 4760.37
A13: NET DEBT / (NET CASH) BRIDGE — as at 30-Jun-2026
A14: Cash and cash equivalents (C$mm) | B14: 449 | D14: Q2 2026 press release.
A15: Long-term debt (C$mm) | B15: 0 | D15: No long-term debt outstanding.
A16: Net (cash) debt as reported (C$mm) | B16: -329.1 | D16: As reported; includes working capital items, so differs from cash less debt.
A17: Investments in securities (C$mm) | B17: 208 | D17: At 30-Jun-26. AKITA shares received on the Fox Drilling sale were distributed to shareholders 16-Jul-26 — confirm the residual before relying on this.
A18: Undrawn credit facilities (C$mm) | B18: 750 | D18: C$500mm revolver (matures 15-Dec-2029) plus C$250mm EDC delayed-draw term loan.
A20: ENTERPRISE VALUE
A21: Market capitalisation | B21: =B11 -> 4760.37
A22: Plus: net debt / (less: net cash) | B22: =B16 -> -329.1
A23: Enterprise value — before securities (C$mm) | B23: =SUM(B21:B22) -> 4431.27
A24: Less: investments in securities | B24: =-B17 -> -208
A25: Enterprise value — fully adjusted (C$mm) | B25: =B23+B24 -> 4223.27 | D25: Used as the EV basis in Derived_Metrics.
A27: OWNERSHIP — the binding constraint on any take-private
A28: Holder | B28: % held | D28: Note
A29: James H.T. Riddell (Chairman, President & CEO) | B29: 0.3283 | D29: ~47.1mm shares.
A30: Susan Riddell Rose (Director) | B30: 0.1044 | D30: ~15.0mm shares.
A31: Brenda Riddell (Director) | B31: 0.1036 | D31: ~14.9mm shares.
A32: Riddell family — combined | B32: =SUM(B29:B31) -> 0.5363 | D32: A controlling block. No take-private can proceed without it.
A33: Institutions | B33: 0.0802 | D33: Unusually low for a C$4bn+ issuer.
A34: Public companies and individual investors | B34: =1-B32-B33 -> 0.3835
A36: IMPLICATION | B36: A hostile take-private is not available. Any transaction is negotiated with the founding family, and under Canadian MI 61-101 a related-party rollover triggers a formal valuation and majority-of-the-minority approval. Test this before modelling anything else.

Sheet Financials_Hist
A1: Historical Financial Results
A2: C$mm unless noted. Source: Q2 2026 and FY2025 press releases. Note the Grande Prairie disposition closed 31-Jan-2025 — 2024 is not comparable.
A4: C$ millions | B4: FY2024 | C4: FY2025 | D4: Q2 2025 | E4: Q4 2025 | F4: Q1 2026 | G4: Q2 2026 | H4: Note
A5: EARNINGS & CASH FLOW
A6: Net income / (loss) | B6: 335.9 | C6: 1288.7 | D6: 4.2 | E6: -1.9 | F6: 53.2 | G6: 68.3 | H6: FY2025 inflated by the C$3.24bn Grande Prairie disposition gain.
A7: Cash from operating activities | B7: 815.3 | C7: 417.3 | D7: 39.8 | E7: 185.4 | F7: 116.2 | G7: 144.4
A8: Adjusted funds flow (AFF) | B8: 930.3 | C8: 467.2 | D8: 81.5 | E8: 140.1 | F8: 143.4 | G8: 175.6 | H8: Company capital management measure. Closest public proxy for cash EBITDA.
A9: Free cash flow | B9: 37.3 | C9: -385.5 | D9: -85.5 | E9: -84.6 | F9: -146.9 | G9: -128.5 | H9: Negative for six straight quarters — the company is funding a build-out.
A10: CAPITAL EXPENDITURE BY ASSET
A11: Willesden Green | B11: 233.5 | C11: 569.6 | D11: 106.2 | E11: 158.3 | F11: 161.7 | G11: 186.8
A12: Sinclair | B12: 14.5 | C12: 64.9 | D12: 5 | E12: 35 | F12: 59.6 | G12: 99.7 | H12: Ramping hard ahead of Q4 2027 plant start-up.
A13: Kaybob | B13: 172.6 | C13: 121.3 | D13: 40.2 | E13: 20.8 | F13: 31.8 | G13: 3.5 | H13: Now in maintenance mode.
A14: Fox Drilling | B14: 8.4 | C14: 8.5 | D14: 1.6 | E14: 2.2 | F14: 1.5 | G14: 4.3 | H14: Subsidiary sold to AKITA 30-Jun-2026.
A15: Corporate, other and sold assets | B15: 413.2 | C15: 24.2 | D15: 4.6 | E15: -7.7 | F15: 2.3 | G15: 2.4 | H15: FY2024 includes C$414.6mm on assets since sold.
A16: Total capital expenditures | B16: =SUM(B11:B15) -> 842.2 | C16: =SUM(C11:C15) -> 788.5 | D16: =SUM(D11:D15) -> 157.6 | E16: =SUM(E11:E15) -> 208.6 | F16: =SUM(F11:F15) -> 256.9 | G16: =SUM(G11:G15) -> 296.7 | H16: Ties to reported totals: FY24 842.2, FY25 788.5, Q2'26 296.7.
A17: Asset retirement obligations settled | B17: 38.1 | C17: 39 | D17: 3 | E17: 9.4 | F17: 26.5 | G17: 1.5
A18: BALANCE SHEET
A19: Total assets | B19: 4757.5 | C19: 3587.2 | D19: 3517.9 | E19: n/a | F19: 3746.7 | G19: 3832.1
A20: Investments in securities | B20: 563.9 | C20: 137.3 | D20: 575.3 | E20: n/a | F20: 141.4 | G20: 208
A21: Long-term debt | B21: 173 | C21: 0 | D21: 0 | E21: n/a | F21: 0 | G21: 0 | H21: Debt-free since the Grande Prairie disposition.
A22: Net (cash) debt | B22: 188.4 | C22: -672.8 | D22: -500.9 | E22: n/a | F22: -515.8 | G22: -329.1 | H22: Net cash is being consumed by the capital programme.
A23: Common shares outstanding (mm) | B23: 146.9 | C23: 144.2 | D23: 143.3 | E23: 144.2 | F23: 144.9 | G23: 145.8
A25: DERIVED
A26: AFF / cash from operating activities | B26: =IFERROR(B8/B7,"") -> 1.1410524 | C26: =IFERROR(C8/C7,"") -> 1.1195782 | D26: =IFERROR(D8/D7,"") -> 2.0477387 | E26: =IFERROR(E8/E7,"") -> 0.75566343 | F26: =IFERROR(F8/F7,"") -> 1.2340792 | G26: =IFERROR(G8/G7,"") -> 1.2160665
A27: Capital intensity (capex / AFF) | B27: =IFERROR(B16/B8,"") -> 0.90529937 | C27: =IFERROR(C16/C8,"") -> 1.687714 | D27: =IFERROR(D16/D8,"") -> 1.9337423 | E27: =IFERROR(E16/E8,"") -> 1.4889365 | F27: =IFERROR(F16/F8,"") -> 1.7914923 | G27: =IFERROR(G16/G8,"") -> 1.6896355 | H27: Above 1.0x means outspend. This is the single most important fact about POU today.

Sheet Production_Ops
A1: Production, Realised Pricing & Netbacks
A2: Sales volumes and unit economics. Source: Q2 2026 and FY2025 press releases.
B4: FY2024 | C4: FY2025 | D4: Q2 2025 | E4: Q4 2025 | F4: Q1 2026 | G4: Q2 2026 | H4: Note
A5: SALES VOLUMES BY PRODUCT
A6: Natural gas (MMcf/d) | B6: 306.8 | C6: 131.9 | D6: 103.3 | E6: 133.1 | F6: 144.5 | G6: 144.4
A7: Condensate and oil (Bbl/d) | B7: 40432 | C7: 16402 | D7: 11636 | E7: 19472 | F7: 18137 | G7: 17803
A8: Other NGLs (Bbl/d) | B8: 6920 | C8: 3853 | D8: 2786 | E8: 5318 | F8: 6037 | G8: 5415 | H8: Ethane, propane, butane.
A9: Total (Boe/d) | B9: =B6*1000/6+B7+B8 -> 98485.333 | C9: =C6*1000/6+C7+C8 -> 42238.333 | D9: =D6*1000/6+D7+D8 -> 31638.667 | E9: =E6*1000/6+E7+E8 -> 46973.333 | F9: =F6*1000/6+F7+F8 -> 48257.333 | G9: =G6*1000/6+G7+G8 -> 47284.667 | H9: 6 Mcf : 1 Bbl. Company notes the 2026 value ratio is closer to 60:1.
A10: % liquids | B10: =(B6+B7)/B9 -> 0.41365347 | C10: =(C6+C7)/C9 -> 0.391443 | D10: =(D6+D7)/D9 -> 0.37104282 | E10: =(E6+E7)/E9 -> 0.41736659 | F10: =(F6+F7)/F9 -> 0.37883361 | G10: =(G6+G7)/G9 -> 0.37956068
A11: SALES VOLUMES BY ASSET (Boe/d)
A12: Willesden Green | B12: 7537 | C12: 14161 | D12: 9223 | E12: 25752 | F12: 28750 | G12: 27466 | H12: From ~7 kboe/d in Jan-25 to >29 kboe/d in Dec-25. The growth engine.
A13: Kaybob | B13: 22404 | C13: 21216 | D13: 21962 | E13: 20387 | F13: 19088 | G13: 19413 | H13: Maintenance: company guides 19-20 kboe/d through 2028.
A14: Other properties | B14: 1226 | C14: 770 | D14: 446 | E14: 834 | F14: 417 | G14: 400
A15: Sold assets (Karr, Wapiti, Zama) | B15: 67323 | C15: 6091 | D15: 0 | E15: 0 | F15: 0 | G15: 0 | H15: Disposed 31-Jan-2025 for C$3.243bn.
A16: Total (Boe/d) | B16: =SUM(B12:B15) -> 98490 | C16: =SUM(C12:C15) -> 42238 | D16: =SUM(D12:D15) -> 31631 | E16: =SUM(E12:E15) -> 46973 | F16: =SUM(F12:F15) -> 48255 | G16: =SUM(G12:G15) -> 47279 | H16: Cross-check: must equal the by-product total above.
A17: REALISED PRICING
A18: Natural gas (C$/Mcf) | B18: 1.99 | C18: 3.02 | D18: 3.07 | E18: 3.58 | F18: 3.52 | G18: 2.5 | H18: ~48% of remaining-2026 gas priced ex-AECO at Dawn, Malin, Emerson.
A19: Condensate and oil (C$/Bbl) | B19: 96.96 | C19: 85.4 | D19: 82.84 | E19: 76.66 | F19: 96.27 | G19: 126.96 | H19: Condensate is the value driver, not gas.
A20: Other NGLs (C$/Bbl) | B20: 35.37 | C20: 30.46 | D20: 27.02 | E20: 27.15 | F20: 30.61 | G20: 38.5
A21: NETBACK BUILD (C$/Boe)
A22: Petroleum and natural gas sales | B22: 48.83 | C22: 47.77 | D22: 44.2 | E22: 45.92 | F22: 52.65 | G22: 60.59
A23: Royalties | B23: -6.18 | C23: -3.31 | D23: -2 | E23: -2.61 | F23: -2.9 | G23: -3.25 | H23: Low: new-well royalty rates on Duvernay volumes.
A24: Operating expense | B24: -13.15 | C24: -11.66 | D24: -12.39 | E24: -9.84 | F24: -9.81 | G24: -8.66 | H24: Five consecutive quarters of decline as owned facilities absorb volume.
A25: Transportation and NGLs processing | B25: -3.76 | C25: -4.47 | D25: -4.57 | E25: -4.81 | F25: -4.83 | G25: -4.75
A26: Net commodities purchased / (sold) | B26: 0.15 | C26: 0.33 | D26: 0.11 | E26: 0.26 | F26: 0.11 | G26: 0.24 | H26: Corporate marketing item, roughly nets to zero.
A27: Netback | B27: =SUM(B22:B26) -> 25.89 | C27: =SUM(C22:C26) -> 28.66 | D27: =SUM(D22:D26) -> 25.35 | E27: =SUM(E22:E26) -> 28.92 | F27: =SUM(F22:F26) -> 35.22 | G27: =SUM(G22:G26) -> 44.17 | H27: Ties to reported: FY24 25.89, FY25 28.66, Q2'26 44.17.
A28: Risk management settlements | B28: 1.01 | C28: 3.3 | D28: 5.16 | E28: 4.73 | F28: -0.46 | G28: -2.48
A29: Netback incl. risk management | B29: =B27+B28 -> 26.9 | C29: =C27+C28 -> 31.96 | D29: =D27+D28 -> 30.51 | E29: =E27+E28 -> 33.65 | F29: =F27+F28 -> 34.76 | G29: =G27+G28 -> 41.69
A30: ASSET-LEVEL UNIT COSTS
A31: Willesden Green operating expense (C$/Boe) | B31: n/a | C31: 6.26 | D31: n/a | E31: 4.71 | F31: n/a | G31: n/a | H31: The structural cost advantage. Company-owned Alhambra plant.
A33: DERIVED — ANNUALISED CASH NETBACK
A34: Netback annualised (C$mm) | B34: =B29*B9*365/1000000 -> 966.97825 | C34: =C29*C9*365/1000000 -> 492.72705 | D34: =D29*D9*365/1000000 -> 352.33294 | E34: =E29*E9*365/1000000 -> 576.93822 | F34: =F29*F9*365/1000000 -> 612.26009 | G34: =G29*G9*365/1000000 -> 719.52368 | H34: Field-level cash generation at the period's volumes and netback. Before G&A, interest and tax.

Sheet Reserves
A1: Reserves — McDaniel Report, effective 31-Dec-2025
A2: Gross reserves. NPV is before tax and does not represent fair market value. Price forecast is the average of Sproule, GLJ and McDaniel decks.
A4: RESERVE VOLUMES
B5: PDP | C5: Total Proved (1P) | D5: Proved + Probable (2P)
A6: Natural gas (Bcf) | B6: 202 | C6: 611 | D6: 2094
A7: NGLs (MBbl) | B7: 23492 | C7: 95890 | D7: 168336
A8: Crude oil (MBbl) | B8: 1988 | C8: 2290 | D8: 4243
A9: Total (MBoe) | B9: =B6*1000/6+B7+B8 -> 59146.667 | C9: =C6*1000/6+C7+C8 -> 200013.33 | D9: =D6*1000/6+D7+D8 -> 521579 | F9: Reported: 59,151 / 199,989 / 521,518 MBoe.
A10: % liquids | B10: =(B7+B8)/B9 -> 0.43079351 | C10: =(C7+C8)/C9 -> 0.49086728 | D10: =(D7+D8)/D9 -> 0.33087797 | F10: 2P is gassier than 1P — Sinclair dry gas dominates the probable book.
A12: BEFORE-TAX NET PRESENT VALUE OF FUTURE NET REVENUE (C$mm)
B13: Volumes (MBoe) | C13: Undiscounted | D13: Discounted at 10%
A14: Total Proved (1P)
A15: Developed | B15: 70266 | C15: 357 | D15: 729
A16: Undeveloped | B16: 129723 | C16: 2485 | D16: 950
A17: Total Proved | B17: =SUM(B15:B16) -> 199989 | C17: =SUM(C15:C16) -> 2842 | D17: =SUM(D15:D16) -> 1679
A18: Proved plus Probable (2P)
A19: Developed | B19: 96568 | C19: 929 | D19: 972
A20: Undeveloped | B20: 424951 | C20: 7401 | D20: 2278
A21: Total Proved plus Probable | B21: =SUM(B19:B20) -> 521519 | C21: =SUM(C19:C20) -> 8330 | D21: =SUM(D19:D20) -> 3250 | F21: 2P NPV10 of C$3,250mm is the anchor for the P/NAV test in Derived_Metrics.
A23: NPV10 PER SHARE — the central valuation tension
A24: 2P NPV10, before tax (C$mm) | B24: =D21 -> 3250
A25: Plus: net cash at 30-Jun-2026 (C$mm) | B25: =-Snapshot!B16 -> 329.1
A26: Adjusted 2P NAV (C$mm) | B26: =SUM(B24:B25) -> 3579.1
A27: Shares outstanding (mm) | B27: =Snapshot!B10 -> 145.8
A28: 2P NAV per share (C$) | B28: =B26/B27 -> 24.548011 | F28: Excludes undeveloped land, infrastructure above reserve value and any resource beyond 2P.
A29: Current share price (C$) | B29: =Snapshot!B6 -> 32.65
A30: Price / 2P NAV | B30: =B29/B28 -> 1.3300467 | F30: Above 1.0x means the market already pays for value the engineered reserve report does not book.
A32: RESERVE LIFE, F&D AND RECYCLE RATIOS (2025)
B33: PDP | C33: Total Proved | D33: Proved + Probable
A34: Reserve life index (years) | B34: 4.5 | C34: 15.2 | D34: 39.5 | F34: PDP RLI of 4.5 years is short — this is a company that must keep drilling.
A35: F&D cost (C$/Boe) | B35: 24.42 | C35: 24.15 | D35: 11.67 | F35: Includes future development capital for Alhambra and Sinclair.
A36: Recycle ratio (x) | B36: 1.2 | C36: 1.2 | D36: 2.5 | F36: 1.2x on a proved basis is thin. The 2.5x on 2P assumes Sinclair is delivered.
A37: 2025 reserve replacement (x) | B37: 2.4 | C37: 5.2 | D37: 21.7

Sheet Guidance
A1: Company Guidance & Capital Plan
A2: Source: Q2 2026 press release (6-Aug-2026), updated from the March 2026 outlook.
A4: 2026 GUIDANCE (revised upward at Q2)
B5: Low | C5: High | D5: Midpoint
A6: Q3 2026 sales volumes (Boe/d) | B6: 50000 | C6: 53000 | D6: =AVERAGE(B6:C6) -> 51500 | F6: 47% liquids.
A7: Q4 2026 sales volumes (Boe/d) | B7: 60000 | C7: 63000 | D7: =AVERAGE(B7:C7) -> 61500 | F7: 49% liquids. Alhambra phase 2 at full rate.
A8: 2026 annual sales volumes (Boe/d) | B8: 51000 | C8: 53000 | D8: =AVERAGE(B8:C8) -> 52000 | F8: 49% liquids. Raised 2,000 Boe/d at midpoint at Q2.
A9: 2026 capital expenditures (C$mm) | B9: 1000 | C9: 1100 | D9: =AVERAGE(B9:C9) -> 1050 | F9: Unchanged.
A10: 2026 abandonment & reclamation (C$mm) | B10: 35 | C10: 35 | D10: =AVERAGE(B10:C10) -> 35
A12: 2027 OUTLOOK
A13: 2027 annual sales volumes (Boe/d) | B13: 60000 | C13: 65000 | D13: =AVERAGE(B13:C13) -> 62500 | F13: 50% liquids.
A14: 2027 exit rate (Boe/d) | B14: 100000 | C14: 100000 | D14: =AVERAGE(B14:C14) -> 100000 | F14: Stated as 'over 100,000', 35% liquids. Roughly double the 2026 average.
A15: 2027 capital expenditures (C$mm) | B15: 1000 | C15: 1000 | D15: =AVERAGE(B15:C15) -> 1000 | F15: Midpoint outlook.
A17: CAPITAL ALLOCATION BY ASSET (C$mm, March 2026 outlook)
B18: 2026 | C18: 2027
A19: Willesden Green | B19: 630 | C19: 440 | F19: Drilling to fill Alhambra phase 2, plus the Leafland interconnect.
A20: Sinclair | B20: 360 | C20: 440 | F20: Plant construction and 15 wells in 2026, completions and tie-ins in 2027.
A21: Kaybob and corporate | B21: 110 | C21: 120 | F21: Balancing figure to the stated midpoint.
A22: Total | B22: =SUM(B19:B21) -> 1100 | C22: =SUM(C19:C21) -> 1000
A24: THE FUNDING GAP — why this is not a conventional LBO candidate
B25: 2026E | C25: 2027E
A26: Adjusted funds flow — analyst placeholder (C$mm) | B26: 700 | C26: 950 | F26: PLACEHOLDER. Replace with output of the operating model in Module 2. 2026E is roughly H1 annualised.
A27: Less: capital expenditures | B27: =-B22 -> -1100 | C27: =-C22 -> -1000
A28: Less: abandonment & reclamation | B28: -35 | C28: -35
A29: Free cash flow before dividends (C$mm) | B29: =SUM(B26:B28) -> -435 | C29: =SUM(C26:C28) -> -85
A30: Less: dividends at C$0.60/share annualised | B30: =-0.6*Snapshot!B10 -> -87.48 | C30: =-0.6*Snapshot!B10 -> -87.48
A31: Cumulative funding requirement (C$mm) | B31: =B29+B30 -> -522.48 | C31: =B31+C29+C30 -> -694.96 | F31: Compare against C$449mm cash plus C$750mm undrawn facilities. A sponsor's leverage competes with this programme for the same balance sheet.

Sheet Assets
A1: Asset Descriptors
A2: Inputs to asset-level type curves and the NAV build. Source: Q2 2026 and FY2025 press releases.
B4: Willesden Green Duvernay | C4: Sinclair Montney | D4: Kaybob | E4: Other / legacy
A5: Status | B5: Producing, ramping | C5: Under construction, first gas Q4 2027 | D5: Producing, maintenance mode | E5: Undeveloped land bank
A6: Q2 2026 volumes (Boe/d) | B6: 27,466 (55% liquids) | C6: Nil | D6: 19,413 (40% liquids) | E6: 400
A7: Net acres | B7: Over 350,000 | C7: Over 170,000 | D7: 110,000 Duvernay + 180,000 Montney | E7: 1.3mm heavy oil; 110k Muskwa; 195k Besa River; 170k NWT
A8: Processing capacity | B8: Alhambra 20,000 Bbl/d + 100 MMcf/d raw after phase 2; Leafland 6,000 Bbl/d + 22 MMcf/d | C8: Sinclair Plant designed for 400 MMcf/d raw | D8: Company-owned gathering and processing | E8: None
A9: Expansion optionality | B9: Phase 3 adds 50 MMcf/d + 10,000 Bbl/d; FID possible Q4 2026, start-up as early as H2 2028 | C9: Land position supports a higher plateau than currently targeted | D9: None planned | E9: Requires capital and a commodity view
A10: Contracted egress | B10: In place | C10: 335 MMcf/d firm from Q4 2027 | D10: In place | E10: n/a
A11: Well results | B11: 210-day peak ~1,240 Boe/d (56% liquids) across 16 wells; 13 of 16 paid out in ~8 months | C11: Test rates 34 MMcf/d upper bench, 25 MMcf/d lower bench — highest publicly recorded in Alberta Montney | D11: Duvernay wells offsetting decline | E11: n/a
A12: Plateau target | B12: ~50,000 Boe/d sustainable over 20+ years | C12: Over 300 MMcf/d of sales gas | D12: 19,000-20,000 Boe/d through 2028 | E12: n/a
A13: Unit operating cost | B13: C$4.71/Boe in Q4 2025 | C13: Designed as high-rate, low-cost dry gas | D13: Higher — legacy conventional mix | E13: n/a
A14: Key risk for the model | B14: Type-curve durability past 300 days; wells are choked, so declines are managed not natural | C14: Single-asset execution risk: plant on time and on budget, and gas price at start-up | D14: Decline once Duvernay drilling stops | E14: Zero value in most NAV cases; option value only
A16: TOTAL LAND POSITION AT 31-DEC-2025 (thousand acres) | B16: Gross | C16: Net
A17: Acreage assigned reserves | B17: 852 | C17: 704
A18: Acreage not assigned reserves | B18: 3363 | C18: 2349
A19: Total | B19: =SUM(B17:B18) -> 4215 | C19: =SUM(C17:C18) -> 3053

Sheet Hedges_Credit
A1: Hedge Book & Credit Facilities
A2: As disclosed in the Q2 2026 press release (6-Aug-2026).
A4: COMMODITY AND FX CONTRACTS
A5: Instrument | B5: Notional | C5: Price / rate | D5: Remaining term | E5: Note
A6: NYMEX WTI swap (sale) | B6: 7,000 Bbl/d | C6: C$109.19/Bbl | D6: Jul 2026 - Dec 2026 | E6: Roughly 39% of Q2 liquids volumes.
A7: NYMEX WTI swap (sale) | B7: 6,000 Bbl/d | C7: C$100.34/Bbl | D7: Jan 2027 - Dec 2027 | E7: Coverage falls as volumes double — 2027 is largely unhedged.
A8: Citygate / Malin basis swap | B8: 10,000 MMBtu/d | C8: Citygate less US$0.97/MMBtu | D8: Jul 2026 - Oct 2028 | E8: Basis only, no flat-price protection.
A9: FX average rate forward (sale) | B9: US$10mm / month | C9: 1.3810 CAD/USD | D9: Jul 2026 - Dec 2026
A10: FX average rate forward (sale) | B10: US$10mm / month | C10: 1.3680 CAD/USD | D10: Jan 2027 - Dec 2027
A12: Observation | B12: There is no flat-price natural gas hedge. Sinclair is a dry gas project reaching first production in Q4 2027 into an unhedged market. A sponsor with leverage would need a materially larger hedge book, which costs upside — model this explicitly in the LBO.
A14: CREDIT FACILITIES
A15: Senior secured revolving bank credit facility (C$mm) | B15: 500 | E15: Covenant-based. Maturity extended to 15-Dec-2029.
A16: EDC non-revolving delayed-draw term loan (C$mm) | B16: 250 | E16: Five-year, non-amortising. Secured December 2025.
A17: Total facilities (C$mm) | B17: =SUM(B15:B16) -> 750 | E17: Fully undrawn at 30-Jun-2026.
A18: Cash and cash equivalents (C$mm) | B18: =Snapshot!B14 -> 449 | E18: Links to Snapshot.
A19: Total liquidity (C$mm) | B19: =B17+B18 -> 1199

Sheet PriceDeck
A1: Commodity Price Deck — Bear / Base / Bull
A2: THE central scenario lever. Every yellow cell is an assumption you own and must defend. The Monte Carlo module samples around the Base column.
A4: Active scenario (1 = Bear, 2 = Base, 3 = Bull) | B4: 2 | H4: Downstream models read the 'Active' block at the bottom of this sheet.
A6: BEAR CASE
B7: 2026E | C7: 2027E | D7: 2028E | E7: 2029E | F7: 2030E
A8: WTI (US$/Bbl) | B8: 76 | C8: 62 | D8: 58 | E8: 58 | F8: 58
A9: AECO (C$/GJ) | B9: 1.9 | C9: 1.8 | D9: 1.9 | E9: 2 | F9: 2.1
A10: Dawn / diversified premium (C$/GJ) | B10: 0.7 | C10: 0.7 | D10: 0.7 | E10: 0.7 | F10: 0.7
A11: CAD/USD exchange rate | B11: 1.38 | C11: 1.4 | D11: 1.42 | E11: 1.42 | F11: 1.42
A12: Condensate differential to WTI (C$/Bbl) | B12: -2 | C12: -2 | D12: -2 | E12: -2 | F12: -2
A14: BASE CASE
B15: 2026E | C15: 2027E | D15: 2028E | E15: 2029E | F15: 2030E
A16: WTI (US$/Bbl) | B16: 80 | C16: 75 | D16: 72 | E16: 70 | F16: 70
A17: AECO (C$/GJ) | B17: 2.4 | C17: 2.9 | D17: 3.2 | E17: 3.3 | F17: 3.4
A18: Dawn / diversified premium (C$/GJ) | B18: 0.9 | C18: 0.9 | D18: 0.9 | E18: 0.9 | F18: 0.9
A19: CAD/USD exchange rate | B19: 1.37 | C19: 1.36 | D19: 1.35 | E19: 1.35 | F19: 1.35
A20: Condensate differential to WTI (C$/Bbl) | B20: 0 | C20: 0 | D20: 0 | E20: 0 | F20: 0
A22: BULL CASE
B23: 2026E | C23: 2027E | D23: 2028E | E23: 2029E | F23: 2030E
A24: WTI (US$/Bbl) | B24: 84 | C24: 95 | D24: 92 | E24: 90 | F24: 88
A25: AECO (C$/GJ) | B25: 3 | C25: 4 | D25: 4.5 | E25: 4.75 | F25: 5
A26: Dawn / diversified premium (C$/GJ) | B26: 1.1 | C26: 1.2 | D26: 1.2 | E26: 1.2 | F26: 1.2
A27: CAD/USD exchange rate | B27: 1.35 | C27: 1.33 | D27: 1.32 | E27: 1.32 | F27: 1.32
A28: Condensate differential to WTI (C$/Bbl) | B28: 2 | C28: 2 | D28: 2 | E28: 2 | F28: 2
A30: Sinclair start-up delay (years) — Bull / Base / Bear | B30: 0 | C30: 0.5 | D30: 1 | H30: Non-price lever. Slippage at Sinclair moves the case more than a dollar of WTI.
A32: ACTIVE DECK — read by all downstream models
B33: 2026E | C33: 2027E | D33: 2028E | E33: 2029E | F33: 2030E
A34: WTI (US$/Bbl) | B34: =IF($B$4=1,B8,IF($B$4=3,B24,B16)) -> 80 | C34: =IF($B$4=1,C8,IF($B$4=3,C24,C16)) -> 75 | D34: =IF($B$4=1,D8,IF($B$4=3,D24,D16)) -> 72 | E34: =IF($B$4=1,E8,IF($B$4=3,E24,E16)) -> 70 | F34: =IF($B$4=1,F8,IF($B$4=3,F24,F16)) -> 70
A35: AECO (C$/GJ) | B35: =IF($B$4=1,B9,IF($B$4=3,B25,B17)) -> 2.4 | C35: =IF($B$4=1,C9,IF($B$4=3,C25,C17)) -> 2.9 | D35: =IF($B$4=1,D9,IF($B$4=3,D25,D17)) -> 3.2 | E35: =IF($B$4=1,E9,IF($B$4=3,E25,E17)) -> 3.3 | F35: =IF($B$4=1,F9,IF($B$4=3,F25,F17)) -> 3.4
A36: Dawn / diversified premium (C$/GJ) | B36: =IF($B$4=1,B10,IF($B$4=3,B26,B18)) -> 0.9 | C36: =IF($B$4=1,C10,IF($B$4=3,C26,C18)) -> 0.9 | D36: =IF($B$4=1,D10,IF($B$4=3,D26,D18)) -> 0.9 | E36: =IF($B$4=1,E10,IF($B$4=3,E26,E18)) -> 0.9 | F36: =IF($B$4=1,F10,IF($B$4=3,F26,F18)) -> 0.9
A37: CAD/USD exchange rate | B37: =IF($B$4=1,B11,IF($B$4=3,B27,B19)) -> 1.37 | C37: =IF($B$4=1,C11,IF($B$4=3,C27,C19)) -> 1.36 | D37: =IF($B$4=1,D11,IF($B$4=3,D27,D19)) -> 1.35 | E37: =IF($B$4=1,E11,IF($B$4=3,E27,E19)) -> 1.35 | F37: =IF($B$4=1,F11,IF($B$4=3,F27,F19)) -> 1.35
A38: Condensate differential to WTI (C$/Bbl) | B38: =IF($B$4=1,B12,IF($B$4=3,B28,B20)) -> 0 | C38: =IF($B$4=1,C12,IF($B$4=3,C28,C20)) -> 0 | D38: =IF($B$4=1,D12,IF($B$4=3,D28,D20)) -> 0 | E38: =IF($B$4=1,E12,IF($B$4=3,E28,E20)) -> 0 | F38: =IF($B$4=1,F12,IF($B$4=3,F28,F20)) -> 0
A40: Realised gas price check (C$/Mcf) | B40: =(B35+B36)*1.055 -> 3.4815 | C40: =(C35+C36)*1.055 -> 4.009 | D40: =(D35+D36)*1.055 -> 4.3255 | E40: =(E35+E36)*1.055 -> 4.431 | F40: =(F35+F36)*1.055 -> 4.5365 | H40: Approximate GJ to Mcf conversion of 1.055. Sanity check: FY2025 realised was C$3.02/Mcf.
A41: Condensate price (C$/Bbl) | B41: =B34*B37+B38 -> 109.6 | C41: =C34*C37+C38 -> 102 | D41: =D34*D37+D38 -> 97.2 | E41: =E34*E37+E38 -> 94.5 | F41: =F34*F37+F38 -> 94.5 | H41: Sanity check: Q2 2026 realised condensate and oil was C$126.96/Bbl — a wide premium worth investigating.
A43: HEALTH WARNING | B43: These decks are illustrative starting points, not forecasts. Before the investment committee module, replace them with the forward strip on your valuation date and cite it. A case study is judged on whether its assumptions are defensible, not on whether the IRR is high.

Sheet Derived_Metrics
A1: Trading Multiples — Where POU Trades Today
A2: Live off Snapshot, Reserves and Production_Ops. This is the 'entry price' evidence for the investment committee.
A4: INPUTS
A5: Share price (C$) | B5: =Snapshot!B6 -> 32.65
A6: Shares outstanding (mm) | B6: =Snapshot!B10 -> 145.8
A7: Market capitalisation (C$mm) | B7: =Snapshot!B11 -> 4760.37
A8: Enterprise value, fully adjusted (C$mm) | B8: =Snapshot!B25 -> 4223.27 | D8: Market cap less net cash and securities.
A9: Q2 2026 production (Boe/d) | B9: =Production_Ops!G9 -> 47284.667
A10: Q4 2026E production, midpoint (Boe/d) | B10: =Guidance!D7 -> 61500 | D10: Guided exit-quarter rate.
A11: Q2 2026 AFF annualised (C$mm) | B11: =Financials_Hist!G8*4 -> 702.4 | D11: Crude annualisation. Replace with the operating model output in Module 2.
A12: H1 2026 AFF annualised (C$mm) | B12: =(Financials_Hist!F8+Financials_Hist!G8)*2 -> 638
A13: 2P reserves (MBoe) | B13: =Reserves!D9 -> 521579
A14: 2P NPV10 before tax (C$mm) | B14: =Reserves!D21 -> 3250
A16: MULTIPLES
A17: EV / AFF — annualised Q2 2026 | B17: =B8/B11 -> 6.0126281 | D17: Canadian intermediate producers have generally traded in a 3-5x band on cash flow. Verify against a live comp set.
A18: EV / AFF — annualised H1 2026 | B18: =B8/B12 -> 6.6195455
A19: EV / flowing barrel — Q2 2026 (C$/Boe/d) | B19: =B8*1000000/B9 -> 89315.846 | D19: Recent Canadian liquids-rich deals have cleared roughly C$50,000-90,000/Boe/d. Confirm with current transactions.
A20: EV / flowing barrel — Q4 2026E (C$/Boe/d) | B20: =B8*1000000/B10 -> 68671.057 | D20: The forward number. The gap between these two rows is what you are being asked to pay for growth.
A21: EV / 2P reserves (C$/Boe) | B21: =B8*1000/B13 -> 8.097086
A22: Market cap / 2P NPV10 (P/NAV) | B22: =B7/B14 -> 1.4647292 | D22: Above 1.0x means the market pays more than the engineered before-tax reserve value.
A23: 2P NPV10 per share (C$) | B23: =B14/B6 -> 22.290809
A24: Implied premium in the share price to 2P NPV10 per share | B24: =B5/(B14/B6)-1 -> 0.46472923
A26: TAKE-PRIVATE PRICE LADDER — what a bid would have to clear
A27: Premium to market | B27: Offer (C$/sh) | D27: Implied equity cheque and P/NAV
A28: 0 | B28: =B5*(1+A28) -> 32.65 | D28: ="Equity value C$"&TEXT(B28*B6,"#,##0")&"mm | P/NAV "&TEXT(B28*B6/B14,"0.00")&"x" -> Equity value C$4,760mm | P/NAV 1.46x
A29: 0.15 | B29: =B5*(1+A29) -> 37.5475 | D29: ="Equity value C$"&TEXT(B29*B6,"#,##0")&"mm | P/NAV "&TEXT(B29*B6/B14,"0.00")&"x" -> Equity value C$5,474mm | P/NAV 1.68x
A30: 0.25 | B30: =B5*(1+A30) -> 40.8125 | D30: ="Equity value C$"&TEXT(B30*B6,"#,##0")&"mm | P/NAV "&TEXT(B30*B6/B14,"0.00")&"x" -> Equity value C$5,950mm | P/NAV 1.83x
A31: 0.35 | B31: =B5*(1+A31) -> 44.0775 | D31: ="Equity value C$"&TEXT(B31*B6,"#,##0")&"mm | P/NAV "&TEXT(B31*B6/B14,"0.00")&"x" -> Equity value C$6,426mm | P/NAV 1.98x
A33: READ THIS BEFORE MODULE 2 | B33: If a 25-35% control premium puts the purchase price at a large multiple of 2P NPV10, the whole return depends on value the reserve report does not yet book: Sinclair, the Alhambra phase 3 expansion, and the undeveloped land. Your NAV module must value those explicitly and defensibly, because that is where the entire thesis lives.
